rsptx/build_tools/__init__.py
rsptx/build_tools/build.py
rsptx/build_tools/cleanup_docker.sh
rsptx/build_tools/core.py
rsptx/cl_utils/__init__.py
rsptx/cl_utils/core.py
rsptx/configuration/__init__.py
rsptx/configuration/core.py
rsptx/data_types/__init__.py
rsptx/data_types/autograde.py
rsptx/data_types/language.py
rsptx/data_types/question_type.py
rsptx/data_types/which_to_grade.py
rsptx/db/__init__.py
rsptx/db/async_session.py
rsptx/db/core.py
rsptx/db/crud/__init__.py
rsptx/db/crud/assignment.py
rsptx/db/crud/book.py
rsptx/db/crud/course.py
rsptx/db/crud/course_attrs.py
rsptx/db/crud/crud.py
rsptx/db/crud/group.py
rsptx/db/crud/library.py
rsptx/db/crud/lti.py
rsptx/db/crud/peer.py
rsptx/db/crud/practice.py
rsptx/db/crud/question.py
rsptx/db/crud/rsfiles.py
rsptx/db/crud/rslogging.py
rsptx/db/crud/scoring.py
rsptx/db/crud/selectq.py
rsptx/db/crud/timed.py
rsptx/db/crud/user.py
rsptx/db/models.py
rsptx/db/sync_session.py
rsptx/logging/__init__.py
rsptx/logging/applogger.py
rsptx/logging/core.py
rsptx/response_helpers/__init__.py
rsptx/response_helpers/core.py
rsptx/validation/__init__.py
rsptx/validation/core.py
rsptx/validation/schemas.py
runestone/__init__.py
runestone/__main__.py
runestone/accessibility/__init__.py
runestone/accessibility/accessibility.py
runestone/accessibility/css/accessibility.css
runestone/accessibility/css/accessibilitydarkest.css
runestone/accessibility/css/accessibilitylight.css
runestone/activecode/LabTestHelper.java
runestone/activecode/__init__.py
runestone/activecode/activecode.py
runestone/activecode/css/activecode.less
runestone/activecode/css/codemirror-dark.less
runestone/activecode/textfield.py
runestone/animation/__init__.py
runestone/animation/animation.py
runestone/animation/js/animationbase.js
runestone/animation/js/sortmodels.js
runestone/animation/js/sortviewers.js
runestone/assignment/__init__.py
runestone/blockly/__init__.py
runestone/blockly/blockly.py
runestone/cellbotics/__init__.py
runestone/chapterdb/__init__.py
runestone-7.11.12.dist-info/METADATA
runestone-7.11.12.dist-info/WHEEL
runestone-7.11.12.dist-info/entry_points.txt
runestone-7.11.12.dist-info/RECORD
