Metadata-Version: 2.3
Name: runestone
Version: 7.11.12
Summary: Sphinx extensions for writing interactive documents.
License: GPL
Keywords: runestone,sphinx,ebook,oer,education
Author: Brad Miller
Author-email: bonelake@mac.com
Requires-Python: >=3.10.0,<4.0.0
Classifier: Development Status :: 5 - Production/Stable
Classifier: Environment :: Console
Classifier: Environment :: Plugins
Classifier: Environment :: Web Environment
Classifier: Framework :: Sphinx :: Extension
Classifier: Intended Audience :: Education
Classifier: License :: OSI Approved :: GNU General Public License v3 or later (GPLv3+)
Classifier: License :: Other/Proprietary License
Classifier: Operating System :: MacOS
Classifier: Operating System :: Unix
Classifier: Programming Language :: Python
Classifier: Programming Language :: Python :: 3
Classifier: Programming Language :: Python :: 3.10
Classifier: Programming Language :: Python :: 3.11
Classifier: Programming Language :: Python :: 3.12
Classifier: Programming Language :: Python :: 3.13
Classifier: Programming Language :: Python :: 3.7
Classifier: Programming Language :: Python :: 3.8
Classifier: Programming Language :: Python :: 3.9
Classifier: Topic :: Education
Classifier: Topic :: Text Processing :: Markup
Requires-Dist: CodeChat (==1.9.3)
Requires-Dist: Paver (>=1.2.4)
Requires-Dist: SQLAlchemy (>=2.0.0,<3.0.0)
Requires-Dist: Sphinx (>=5.0.0,<6.0.0)
Requires-Dist: aiosqlite (>=0.18.0)
Requires-Dist: asyncpg (>=0.30.0,<0.31.0)
Requires-Dist: click (>=8,<9)
Requires-Dist: cogapp (>=2.5)
Requires-Dist: cryptography (>=3.0.0,<4.0.0)
Requires-Dist: dateutils (>=0.6.12,<0.7.0)
Requires-Dist: fastapi (>=0.115.0,<0.116.0)
Requires-Dist: greenlet (>=3.0.0,<4.0.0)
Requires-Dist: ipyleaflet (>=0.19.2,<0.20.0)
Requires-Dist: jinja2 (>=3.1.0,<4.0.0)
Requires-Dist: json2xml (>=3.21.0,<4.0.0)
Requires-Dist: jupyter-sphinx (<0.5)
Requires-Dist: jupyterlab (>=4.2.4,<5.0.0)
Requires-Dist: jupyterlite-sphinx (>=0.9.3,<0.10.0)
Requires-Dist: lxml (>=6.0,<7.0)
Requires-Dist: myst-parser (>=1.0.0,<2.0.0)
Requires-Dist: pretext (>=2.35.0,<3.0.0)
Requires-Dist: psycopg2-binary (>=2.9.6,<3.0.0)
Requires-Dist: pydal (>=20230521.1)
Requires-Dist: pydantic (>=2.0.0,<3.0.0)
Requires-Dist: pydantic-settings (>=2.0.3,<3.0.0)
Requires-Dist: pyhumps (>=3.8.0,<4.0.0)
Requires-Dist: python-dotenv (>=1.0.0,<2.0.0)
Requires-Dist: scikit-learn (>=1.5.1,<2.0.0)
Requires-Dist: six (>1.12)
Requires-Dist: sphinx-reredirects (>=0.1.2,<0.2.0)
Requires-Dist: sphinxcontrib-paverutils (>=1.18.1)
Requires-Dist: toml (>=0.10.2,<0.11.0)
Project-URL: Documentation, https://runestone-monorepo.readthedocs.io/en/latest/index.html
Project-URL: Repository, https://github.com/RunestoneInteractive/rs
